{
  "legislative_session": "69",
  "identifier": "SB 2222",
  "title": "A BILL for an Act to create and enact two new sections to chapter 25-13 of the North Dakota Century Code, relating to the certification and sale of assistance animals; to amend and reenact sections 25-13-01.1 and 47-16-07.5 of the North Dakota Century Code, relating to definitions associated with assistance animals and disability documentation for a service or assistance animal in a rental dwelling; and to provide a penalty.",
  "from_organization": "~{\"classification\": \"upper\"}",
  "classification": [
    "bill"
  ],
  "subject": [],
  "abstracts": [
    {
      "note": "summary",
      "abstract": "Relating to the certification and sale of assistance animals; to amend and reenact sections 25\u201113\u201101.1 and 47\u201116\u201107.5 of the North Dakota Century Code, relating to definitions associated with assistance animals and disability documentation for a service or assistance animal in a rental dwelling; and to provide a penalty."
    }
  ],
  "other_titles": [],
  "other_identifiers": [],
  "actions": [
    {
      "description": "Introduced, first reading, referred Industry and Business Committee",
      "date": "2025-01-17",
      "organization_id": "~{\"classification\": \"upper\"}",
      "classification": [
        "introduction"
      ],
      "related_entities": [],
      "_processing": {
        "log_file_created": "2025-10-25T03:09:10Z"
      }
    },
    {
      "description": "Request return from committee",
      "date": "2025-01-23",
      "organization_id": "~{\"classification\": \"upper\"}",
      "classification": [],
      "related_entities": [],
      "_processing": {
        "log_file_created": "2025-10-25T03:09:10Z"
      }
    },
    {
      "description": "Rereferred to Agriculture and Veterans Affairs",
      "date": "2025-01-23",
      "organization_id": "~{\"classification\": \"upper\"}",
      "classification": [],
      "related_entities": [],
      "_processing": {
        "log_file_created": "2025-10-25T03:09:10Z"
      }
    },
    {
      "description": "Committee Hearing 10:30",
      "date": "2025-02-13",
      "organization_id": "~{\"classification\": \"upper\"}",
      "classification": [],
      "related_entities": [],
      "_processing": {
        "log_file_created": "2025-10-25T03:09:10Z"
      }
    },
    {
      "description": "Reported back, do not pass, placed on calendar 6 0 0",
      "date": "2025-02-14",
      "organization_id": "~{\"classification\": \"upper\"}",
      "classification": [
        "committee-passage",
        "committee-passage-unfavorable"
      ],
      "related_entities": [],
      "_processing": {
        "log_file_created": "2025-10-25T03:09:10Z"
      }
    },
    {
      "description": "Second reading, failed to pass, yeas 1 nays 44",
      "date": "2025-02-17",
      "organization_id": "~{\"classification\": \"upper\"}",
      "classification": [
        "reading-2"
      ],
      "related_entities": [],
      "_processing": {
        "log_file_created": "2025-10-25T03:09:10Z"
      }
    }
  ],
  "sponsorships": [
    {
      "name": "Bob Paulson",
      "classification": "primary",
      "entity_type": "person",
      "primary": true,
      "person_id": "~{\"chamber\": \"upper\", \"name\": \"Bob Paulson\"}",
      "organization_id": null
    },
    {
      "name": "Mike Lefor",
      "classification": "cosponsor",
      "entity_type": "person",
      "primary": false,
      "person_id": "~{\"chamber\": \"lower\", \"name\": \"Mike Lefor\"}",
      "organization_id": null
    },
    {
      "name": "Scott Louser",
      "classification": "cosponsor",
      "entity_type": "person",
      "primary": false,
      "person_id": "~{\"chamber\": \"lower\", \"name\": \"Scott Louser\"}",
      "organization_id": null
    },
    {
      "name": "Larry Luick",
      "classification": "cosponsor",
      "entity_type": "person",
      "primary": false,
      "person_id": "~{\"chamber\": \"upper\", \"name\": \"Larry Luick\"}",
      "organization_id": null
    },
    {
      "name": "Matthew Ruby",
      "classification": "cosponsor",
      "entity_type": "person",
      "primary": false,
      "person_id": "~{\"chamber\": \"lower\", \"name\": \"Matthew Ruby\"}",
      "organization_id": null
    },
    {
      "name": "Kent Weston",
      "classification": "cosponsor",
      "entity_type": "person",
      "primary": false,
      "person_id": "~{\"chamber\": \"upper\", \"name\": \"Kent Weston\"}",
      "organization_id": null
    }
  ],
  "related_bills": [],
  "versions": [
    {
      "note": "INTRODUCED",
      "links": [
        {
          "url": "https://ndlegis.gov/assembly/69-2025/regular/documents/25-0815-01000.pdf",
          "media_type": "application/pdf"
        }
      ],
      "date": "",
      "classification": ""
    }
  ],
  "documents": [],
  "citations": [],
  "sources": [
    {
      "url": "https://ndlegis.gov/assembly/69-2025/regular/bill-overview/bo2222.html",
      "note": "HTML bill detail page"
    },
    {
      "url": "https://ndlegis.gov/api/assembly/69-2025/data/bills.json",
      "note": "JSON page of session bills"
    }
  ],
  "extras": {},
  "jurisdiction": {
    "id": "ocd-jurisdiction/country:us/state:nd/government",
    "name": "North Dakota",
    "classification": "state",
    "division_id": "ocd-division/country:us/state:nd"
  },
  "_processing": {
    "logs_latest_update": "2025-10-25T03:09:10Z",
    "text_extraction_latest_update": "2025-10-25T10:02:24.870026Z"
  }
}