{
  "legislative_session": "69",
  "identifier": "HB 1578",
  "title": "AN ACT to create and enact a new subsection to section 57-40.3-04 of the North Dakota Century Code, relating to a motor vehicle excise tax exemption for abandoned motor vehicles; and to amend and reenact subsection 2 of section 23.1-15-07 of the North Dakota Century Code, relating to excise tax on a motor vehicle taken into the custody of a commercial towing service.",
  "from_organization": "~{\"classification\": \"lower\"}",
  "classification": [
    "bill"
  ],
  "subject": [],
  "abstracts": [
    {
      "note": "summary",
      "abstract": "Relating to a motor vehicle excise tax exemption for abandoned motor vehicles; and to amend and reenact subsection 2 of section 23.1\u201115\u201107 of the North Dakota Century Code, relating to excise tax on a motor vehicle taken into the custody of a commercial towing service."
    }
  ],
  "other_titles": [],
  "other_identifiers": [],
  "actions": [
    {
      "description": "Introduced, first reading, referred Transportation Committee",
      "date": "2025-01-20",
      "organization_id": "~{\"classification\": \"lower\"}",
      "classification": [
        "introduction"
      ],
      "related_entities": [],
      "_processing": {
        "log_file_created": "2025-10-25T03:09:07Z"
      }
    },
    {
      "description": "Committee Hearing 09:00",
      "date": "2025-02-07",
      "organization_id": "~{\"classification\": \"lower\"}",
      "classification": [],
      "related_entities": [],
      "_processing": {
        "log_file_created": "2025-10-25T03:09:07Z"
      }
    },
    {
      "description": "Reported back, do pass, place on calendar 12 0 2",
      "date": "2025-02-07",
      "organization_id": "~{\"classification\": \"lower\"}",
      "classification": [
        "committee-passage",
        "committee-passage-favorable"
      ],
      "related_entities": [],
      "_processing": {
        "log_file_created": "2025-10-25T03:09:07Z"
      }
    },
    {
      "description": "Second reading, passed, yeas 89 nays 1",
      "date": "2025-02-10",
      "organization_id": "~{\"classification\": \"lower\"}",
      "classification": [
        "passage",
        "reading-2"
      ],
      "related_entities": [],
      "_processing": {
        "log_file_created": "2025-10-25T03:09:07Z"
      }
    },
    {
      "description": "Received from House",
      "date": "2025-02-11",
      "organization_id": "~{\"classification\": \"upper\"}",
      "classification": [],
      "related_entities": [],
      "_processing": {
        "log_file_created": "2025-10-25T03:09:07Z"
      }
    },
    {
      "description": "Introduced, first reading, referred Transportation Committee",
      "date": "2025-03-11",
      "organization_id": "~{\"classification\": \"upper\"}",
      "classification": [
        "introduction"
      ],
      "related_entities": [],
      "_processing": {
        "log_file_created": "2025-10-25T03:09:07Z"
      }
    },
    {
      "description": "Committee Hearing 09:00",
      "date": "2025-03-20",
      "organization_id": "~{\"classification\": \"upper\"}",
      "classification": [],
      "related_entities": [],
      "_processing": {
        "log_file_created": "2025-10-25T03:09:07Z"
      }
    },
    {
      "description": "Reported back, do pass, place on calendar 6 0 0",
      "date": "2025-03-20",
      "organization_id": "~{\"classification\": \"upper\"}",
      "classification": [
        "committee-passage",
        "committee-passage-favorable"
      ],
      "related_entities": [],
      "_processing": {
        "log_file_created": "2025-10-25T03:09:07Z"
      }
    },
    {
      "description": "Second reading, passed, yeas 44 nays 0",
      "date": "2025-03-21",
      "organization_id": "~{\"classification\": \"upper\"}",
      "classification": [
        "passage",
        "reading-2"
      ],
      "related_entities": [],
      "_processing": {
        "log_file_created": "2025-10-25T03:09:07Z"
      }
    },
    {
      "description": "Returned to House",
      "date": "2025-03-24",
      "organization_id": "~{\"classification\": \"lower\"}",
      "classification": [],
      "related_entities": [],
      "_processing": {
        "log_file_created": "2025-10-25T03:09:07Z"
      }
    },
    {
      "description": "Signed by President",
      "date": "2025-03-25",
      "organization_id": "~{\"classification\": \"upper\"}",
      "classification": [],
      "related_entities": [],
      "_processing": {
        "log_file_created": "2025-10-25T03:09:07Z"
      }
    },
    {
      "description": "Signed by Speaker",
      "date": "2025-03-26",
      "organization_id": "~{\"classification\": \"lower\"}",
      "classification": [],
      "related_entities": [],
      "_processing": {
        "log_file_created": "2025-10-25T03:09:07Z"
      }
    },
    {
      "description": "Sent to Governor",
      "date": "2025-03-26",
      "organization_id": "~{\"classification\": \"lower\"}",
      "classification": [
        "executive-receipt"
      ],
      "related_entities": [],
      "_processing": {
        "log_file_created": "2025-10-25T03:09:07Z"
      }
    },
    {
      "description": "Signed by Governor 03/27",
      "date": "2025-04-01",
      "organization_id": "~{\"classification\": \"lower\"}",
      "classification": [
        "executive-signature"
      ],
      "related_entities": [],
      "_processing": {
        "log_file_created": "2025-10-25T03:09:07Z"
      }
    },
    {
      "description": "Filed with Secretary Of State 03/31",
      "date": "2025-04-02",
      "organization_id": "~{\"classification\": \"legislature\"}",
      "classification": [
        "introduction"
      ],
      "related_entities": [],
      "_processing": {
        "log_file_created": "2025-10-25T03:09:07Z"
      }
    }
  ],
  "sponsorships": [
    {
      "name": "Jim Grueneich",
      "classification": "primary",
      "entity_type": "person",
      "primary": true,
      "person_id": "~{\"chamber\": \"lower\", \"name\": \"Jim Grueneich\"}",
      "organization_id": null
    },
    {
      "name": "Mike Brandenburg",
      "classification": "cosponsor",
      "entity_type": "person",
      "primary": false,
      "person_id": "~{\"chamber\": \"lower\", \"name\": \"Mike Brandenburg\"}",
      "organization_id": null
    },
    {
      "name": "Cole Conley",
      "classification": "cosponsor",
      "entity_type": "person",
      "primary": false,
      "person_id": "~{\"chamber\": \"upper\", \"name\": \"Cole Conley\"}",
      "organization_id": null
    },
    {
      "name": "Claire Cory",
      "classification": "cosponsor",
      "entity_type": "person",
      "primary": false,
      "person_id": "~{\"chamber\": \"upper\", \"name\": \"Claire Cory\"}",
      "organization_id": null
    },
    {
      "name": "Ben Koppelman",
      "classification": "cosponsor",
      "entity_type": "person",
      "primary": false,
      "person_id": "~{\"chamber\": \"lower\", \"name\": \"Ben Koppelman\"}",
      "organization_id": null
    },
    {
      "name": "Emily O'Brien",
      "classification": "cosponsor",
      "entity_type": "person",
      "primary": false,
      "person_id": "~{\"chamber\": \"lower\", \"name\": \"Emily O'Brien\"}",
      "organization_id": null
    },
    {
      "name": "Steve Vetter",
      "classification": "cosponsor",
      "entity_type": "person",
      "primary": false,
      "person_id": "~{\"chamber\": \"lower\", \"name\": \"Steve Vetter\"}",
      "organization_id": null
    },
    {
      "name": "Robin Weisz",
      "classification": "cosponsor",
      "entity_type": "person",
      "primary": false,
      "person_id": "~{\"chamber\": \"lower\", \"name\": \"Robin Weisz\"}",
      "organization_id": null
    }
  ],
  "related_bills": [],
  "versions": [
    {
      "note": "INTRODUCED",
      "links": [
        {
          "url": "https://ndlegis.gov/assembly/69-2025/regular/documents/25-1259-01000.pdf",
          "media_type": "application/pdf"
        }
      ],
      "date": "",
      "classification": ""
    },
    {
      "note": "Enrollment",
      "links": [
        {
          "url": "https://ndlegis.gov/assembly/69-2025/regular/documents/25-1259-02000.pdf",
          "media_type": "application/pdf"
        }
      ],
      "date": "",
      "classification": ""
    }
  ],
  "documents": [],
  "citations": [],
  "sources": [
    {
      "url": "https://ndlegis.gov/assembly/69-2025/regular/bill-overview/bo1578.html",
      "note": "HTML bill detail page"
    },
    {
      "url": "https://ndlegis.gov/api/assembly/69-2025/data/bills.json",
      "note": "JSON page of session bills"
    }
  ],
  "extras": {},
  "jurisdiction": {
    "id": "ocd-jurisdiction/country:us/state:nd/government",
    "name": "North Dakota",
    "classification": "state",
    "division_id": "ocd-division/country:us/state:nd"
  },
  "_processing": {
    "logs_latest_update": "2025-10-25T03:09:07Z"
  }
}