{
  "legislative_session": "69",
  "identifier": "HB 1440",
  "title": "AN ACT to amend and reenact subdivision d of subsection 3 of section 23-12-10 of the North Dakota Century Code, relating to cigar lounges.",
  "from_organization": "~{\"classification\": \"lower\"}",
  "classification": [
    "bill"
  ],
  "subject": [],
  "abstracts": [
    {
      "note": "summary",
      "abstract": "Relating to cigar lounges."
    }
  ],
  "other_titles": [],
  "other_identifiers": [],
  "actions": [
    {
      "description": "Introduced, first reading, referred Finance and Taxation Committee",
      "date": "2025-01-15",
      "organization_id": "~{\"classification\": \"lower\"}",
      "classification": [
        "introduction"
      ],
      "related_entities": [],
      "_processing": {
        "log_file_created": "2025-10-25T03:09:10Z"
      }
    },
    {
      "description": "Committee Hearing 11:00",
      "date": "2025-01-20",
      "organization_id": "~{\"classification\": \"lower\"}",
      "classification": [],
      "related_entities": [],
      "_processing": {
        "log_file_created": "2025-10-25T03:09:10Z"
      }
    },
    {
      "description": "Reported back amended, do pass, amendment placed on calendar 10 2 2",
      "date": "2025-01-20",
      "organization_id": "~{\"classification\": \"lower\"}",
      "classification": [
        "committee-passage",
        "committee-passage-favorable"
      ],
      "related_entities": [],
      "_processing": {
        "log_file_created": "2025-10-25T03:09:10Z"
      }
    },
    {
      "description": "Amendment adopted, placed on calendar",
      "date": "2025-01-21",
      "organization_id": "~{\"classification\": \"lower\"}",
      "classification": [],
      "related_entities": [],
      "_processing": {
        "log_file_created": "2025-10-25T03:09:10Z"
      }
    },
    {
      "description": "Second reading, passed, yeas 81 nays 13",
      "date": "2025-01-22",
      "organization_id": "~{\"classification\": \"lower\"}",
      "classification": [
        "passage",
        "reading-2"
      ],
      "related_entities": [],
      "_processing": {
        "log_file_created": "2025-10-25T03:09:10Z"
      }
    },
    {
      "description": "Received from House",
      "date": "2025-01-23",
      "organization_id": "~{\"classification\": \"upper\"}",
      "classification": [],
      "related_entities": [],
      "_processing": {
        "log_file_created": "2025-10-25T03:09:10Z"
      }
    },
    {
      "description": "Introduced, first reading, referred Finance and Taxation Committee",
      "date": "2025-02-13",
      "organization_id": "~{\"classification\": \"upper\"}",
      "classification": [
        "introduction"
      ],
      "related_entities": [],
      "_processing": {
        "log_file_created": "2025-10-25T03:09:10Z"
      }
    },
    {
      "description": "Committee Hearing 02:30",
      "date": "2025-02-17",
      "organization_id": "~{\"classification\": \"upper\"}",
      "classification": [],
      "related_entities": [],
      "_processing": {
        "log_file_created": "2025-10-25T03:09:10Z"
      }
    },
    {
      "description": "Reported back amended, do pass, amendment placed on calendar 4 2 0",
      "date": "2025-03-07",
      "organization_id": "~{\"classification\": \"upper\"}",
      "classification": [
        "committee-passage",
        "committee-passage-favorable"
      ],
      "related_entities": [],
      "_processing": {
        "log_file_created": "2025-10-25T03:09:10Z"
      }
    },
    {
      "description": "Amendment adopted, placed on calendar",
      "date": "2025-03-07",
      "organization_id": "~{\"classification\": \"upper\"}",
      "classification": [],
      "related_entities": [],
      "_processing": {
        "log_file_created": "2025-10-25T03:09:10Z"
      }
    },
    {
      "description": "Second reading, passed as amended, yeas 39 nays 6",
      "date": "2025-03-10",
      "organization_id": "~{\"classification\": \"upper\"}",
      "classification": [
        "passage",
        "reading-2"
      ],
      "related_entities": [],
      "_processing": {
        "log_file_created": "2025-10-25T03:09:10Z"
      }
    },
    {
      "description": "Returned to House (12)",
      "date": "2025-03-11",
      "organization_id": "~{\"classification\": \"lower\"}",
      "classification": [],
      "related_entities": [],
      "_processing": {
        "log_file_created": "2025-10-25T03:09:10Z"
      }
    },
    {
      "description": "Refused to concur",
      "date": "2025-03-19",
      "organization_id": "~{\"classification\": \"lower\"}",
      "classification": [],
      "related_entities": [],
      "_processing": {
        "log_file_created": "2025-10-25T03:09:10Z"
      }
    },
    {
      "description": "Conference committee appointed Dockter Motschenbacher Dressler",
      "date": "2025-03-19",
      "organization_id": "~{\"classification\": \"lower\"}",
      "classification": [],
      "related_entities": [],
      "_processing": {
        "log_file_created": "2025-10-25T03:09:10Z"
      }
    },
    {
      "description": "Conference committee appointed Powers Marcellais Rummel",
      "date": "2025-03-28",
      "organization_id": "~{\"classification\": \"upper\"}",
      "classification": [],
      "related_entities": [],
      "_processing": {
        "log_file_created": "2025-10-25T03:09:10Z"
      }
    },
    {
      "description": "Reported back from conference committee, in place of, placed on calendar",
      "date": "2025-04-15",
      "organization_id": "~{\"classification\": \"lower\"}",
      "classification": [
        "committee-passage"
      ],
      "related_entities": [],
      "_processing": {
        "log_file_created": "2025-10-25T03:09:10Z"
      }
    },
    {
      "description": "Conference committee report adopted",
      "date": "2025-04-16",
      "organization_id": "~{\"classification\": \"lower\"}",
      "classification": [],
      "related_entities": [],
      "_processing": {
        "log_file_created": "2025-10-25T03:09:10Z"
      }
    },
    {
      "description": "Second reading, passed, yeas 75 nays 17",
      "date": "2025-04-16",
      "organization_id": "~{\"classification\": \"lower\"}",
      "classification": [
        "passage",
        "reading-2"
      ],
      "related_entities": [],
      "_processing": {
        "log_file_created": "2025-10-25T03:09:10Z"
      }
    },
    {
      "description": "Reported back from conference committee, in place of, placed on calendar",
      "date": "2025-04-18",
      "organization_id": "~{\"classification\": \"upper\"}",
      "classification": [
        "committee-passage"
      ],
      "related_entities": [],
      "_processing": {
        "log_file_created": "2025-10-25T03:09:10Z"
      }
    },
    {
      "description": "Conference committee report adopted",
      "date": "2025-04-21",
      "organization_id": "~{\"classification\": \"upper\"}",
      "classification": [],
      "related_entities": [],
      "_processing": {
        "log_file_created": "2025-10-25T03:09:10Z"
      }
    },
    {
      "description": "Second reading, passed as amended, yeas 39 nays 8",
      "date": "2025-04-21",
      "organization_id": "~{\"classification\": \"upper\"}",
      "classification": [
        "passage",
        "reading-2"
      ],
      "related_entities": [],
      "_processing": {
        "log_file_created": "2025-10-25T03:09:10Z"
      }
    },
    {
      "description": "Signed by President",
      "date": "2025-04-22",
      "organization_id": "~{\"classification\": \"upper\"}",
      "classification": [],
      "related_entities": [],
      "_processing": {
        "log_file_created": "2025-10-25T03:09:10Z"
      }
    },
    {
      "description": "Signed by Speaker",
      "date": "2025-04-25",
      "organization_id": "~{\"classification\": \"lower\"}",
      "classification": [],
      "related_entities": [],
      "_processing": {
        "log_file_created": "2025-10-25T03:09:10Z"
      }
    },
    {
      "description": "Sent to Governor",
      "date": "2025-04-25",
      "organization_id": "~{\"classification\": \"lower\"}",
      "classification": [
        "executive-receipt"
      ],
      "related_entities": [],
      "_processing": {
        "log_file_created": "2025-10-25T03:09:10Z"
      }
    },
    {
      "description": "Signed by Governor 04/28",
      "date": "2025-04-29",
      "organization_id": "~{\"classification\": \"lower\"}",
      "classification": [
        "executive-signature"
      ],
      "related_entities": [],
      "_processing": {
        "log_file_created": "2025-10-25T03:09:10Z"
      }
    },
    {
      "description": "Filed with Secretary Of State 04/28",
      "date": "2025-04-30",
      "organization_id": "~{\"classification\": \"legislature\"}",
      "classification": [
        "introduction"
      ],
      "related_entities": [],
      "_processing": {
        "log_file_created": "2025-10-25T03:09:10Z"
      }
    }
  ],
  "sponsorships": [
    {
      "name": "Dan Ruby",
      "classification": "primary",
      "entity_type": "person",
      "primary": true,
      "person_id": "~{\"chamber\": \"lower\", \"name\": \"Dan Ruby\"}",
      "organization_id": null
    },
    {
      "name": "Jason Dockter",
      "classification": "cosponsor",
      "entity_type": "person",
      "primary": false,
      "person_id": "~{\"chamber\": \"lower\", \"name\": \"Jason Dockter\"}",
      "organization_id": null
    },
    {
      "name": "Craig Headland",
      "classification": "cosponsor",
      "entity_type": "person",
      "primary": false,
      "person_id": "~{\"chamber\": \"lower\", \"name\": \"Craig Headland\"}",
      "organization_id": null
    },
    {
      "name": "Jim Kasper",
      "classification": "cosponsor",
      "entity_type": "person",
      "primary": false,
      "person_id": "~{\"chamber\": \"lower\", \"name\": \"Jim Kasper\"}",
      "organization_id": null
    },
    {
      "name": "Andrew Marschall",
      "classification": "cosponsor",
      "entity_type": "person",
      "primary": false,
      "person_id": "~{\"chamber\": \"lower\", \"name\": \"Andrew Marschall\"}",
      "organization_id": null
    },
    {
      "name": "Bob Paulson",
      "classification": "cosponsor",
      "entity_type": "person",
      "primary": false,
      "person_id": "~{\"chamber\": \"upper\", \"name\": \"Bob Paulson\"}",
      "organization_id": null
    },
    {
      "name": "Todd Porter",
      "classification": "cosponsor",
      "entity_type": "person",
      "primary": false,
      "person_id": "~{\"chamber\": \"lower\", \"name\": \"Todd Porter\"}",
      "organization_id": null
    },
    {
      "name": "Karen M. Rohr",
      "classification": "cosponsor",
      "entity_type": "person",
      "primary": false,
      "person_id": "~{\"chamber\": \"lower\", \"name\": \"Karen M. Rohr\"}",
      "organization_id": null
    },
    {
      "name": "Matthew Ruby",
      "classification": "cosponsor",
      "entity_type": "person",
      "primary": false,
      "person_id": "~{\"chamber\": \"lower\", \"name\": \"Matthew Ruby\"}",
      "organization_id": null
    },
    {
      "name": "Kent Weston",
      "classification": "cosponsor",
      "entity_type": "person",
      "primary": false,
      "person_id": "~{\"chamber\": \"upper\", \"name\": \"Kent Weston\"}",
      "organization_id": null
    },
    {
      "name": "Mike Wobbema",
      "classification": "cosponsor",
      "entity_type": "person",
      "primary": false,
      "person_id": "~{\"chamber\": \"upper\", \"name\": \"Mike Wobbema\"}",
      "organization_id": null
    },
    {
      "name": "Christina Wolff",
      "classification": "cosponsor",
      "entity_type": "person",
      "primary": false,
      "person_id": "~{\"chamber\": \"lower\", \"name\": \"Christina Wolff\"}",
      "organization_id": null
    }
  ],
  "related_bills": [],
  "versions": [
    {
      "note": "INTRODUCED",
      "links": [
        {
          "url": "https://ndlegis.gov/assembly/69-2025/regular/documents/25-0298-01000.pdf",
          "media_type": "application/pdf"
        }
      ],
      "date": "",
      "classification": ""
    },
    {
      "note": "FIRST ENGROSSMENT",
      "links": [
        {
          "url": "https://ndlegis.gov/assembly/69-2025/regular/documents/25-0298-02000.pdf",
          "media_type": "application/pdf"
        }
      ],
      "date": "",
      "classification": ""
    },
    {
      "note": "FIRST ENGROSSMENT with Senate Amendments",
      "links": [
        {
          "url": "https://ndlegis.gov/assembly/69-2025/regular/documents/25-0298-03000.pdf",
          "media_type": "application/pdf"
        }
      ],
      "date": "",
      "classification": ""
    },
    {
      "note": "FIRST ENGROSSMENT with Conference Committee Amendments",
      "links": [
        {
          "url": "https://ndlegis.gov/assembly/69-2025/regular/documents/25-0298-04000.pdf",
          "media_type": "application/pdf"
        }
      ],
      "date": "",
      "classification": ""
    },
    {
      "note": "Enrollment",
      "links": [
        {
          "url": "https://ndlegis.gov/assembly/69-2025/regular/documents/25-0298-05000.pdf",
          "media_type": "application/pdf"
        }
      ],
      "date": "",
      "classification": ""
    }
  ],
  "documents": [
    {
      "note": "Adopted by the House Finance and Taxation Committee",
      "links": [
        {
          "url": "https://ndlegis.gov/assembly/69-2025/regular/documents/25-0298-01002m.pdf",
          "media_type": "application/pdf"
        }
      ],
      "date": "",
      "classification": ""
    },
    {
      "note": "Adopted by the Senate Finance and Taxation Committee",
      "links": [
        {
          "url": "https://ndlegis.gov/assembly/69-2025/regular/documents/25-0298-02001m.pdf",
          "media_type": "application/pdf"
        }
      ],
      "date": "",
      "classification": ""
    },
    {
      "note": "Prepared by the Legislative Council staff for Representative Dockter",
      "links": [
        {
          "url": "https://ndlegis.gov/assembly/69-2025/regular/documents/25-0298-02002m.pdf",
          "media_type": "application/pdf"
        }
      ],
      "date": "",
      "classification": ""
    }
  ],
  "citations": [],
  "sources": [
    {
      "url": "https://ndlegis.gov/assembly/69-2025/regular/bill-overview/bo1440.html",
      "note": "HTML bill detail page"
    },
    {
      "url": "https://ndlegis.gov/api/assembly/69-2025/data/bills.json",
      "note": "JSON page of session bills"
    }
  ],
  "extras": {},
  "jurisdiction": {
    "id": "ocd-jurisdiction/country:us/state:nd/government",
    "name": "North Dakota",
    "classification": "state",
    "division_id": "ocd-division/country:us/state:nd"
  },
  "_processing": {
    "logs_latest_update": "2025-10-25T03:09:10Z"
  }
}