{
  "legislative_session": "69",
  "identifier": "SB 2253",
  "title": "AN ACT to create and enact a new subdivision to subsection 2 of section 39-06.1-06 and a new section to chapter 39-21 of the North Dakota Century Code, relating to the use of an engine compression brake device and cities and counties posting a zone prohibiting the use of an engine compression brake device; to amend and reenact section 39-06.1-09 of the North Dakota Century Code, relating to the definition of a moving violation; and to provide a penalty.",
  "from_organization": "~{\"classification\": \"upper\"}",
  "classification": [
    "bill"
  ],
  "subject": [],
  "abstracts": [
    {
      "note": "summary",
      "abstract": "Relating to the use of an engine compression brake device and cities and counties posting a zone prohibiting the use of an engine compression brake device; to amend and reenact section 39\u201106.1\u201109 of the North Dakota Century Code, relating to the definition of a moving violation; and to provide a penalty."
    }
  ],
  "other_titles": [],
  "other_identifiers": [],
  "actions": [
    {
      "description": "Introduced, first reading, referred Transportation Committee",
      "date": "2025-01-23",
      "organization_id": "~{\"classification\": \"upper\"}",
      "classification": [
        "introduction"
      ],
      "related_entities": [],
      "_processing": {
        "log_file_created": "2025-10-25T03:09:07Z"
      }
    },
    {
      "description": "Committee Hearing 10:30",
      "date": "2025-02-06",
      "organization_id": "~{\"classification\": \"upper\"}",
      "classification": [],
      "related_entities": [],
      "_processing": {
        "log_file_created": "2025-10-25T03:09:07Z"
      }
    },
    {
      "description": "Reported back, do pass, place on calendar 6 0 0",
      "date": "2025-02-06",
      "organization_id": "~{\"classification\": \"upper\"}",
      "classification": [
        "committee-passage",
        "committee-passage-favorable"
      ],
      "related_entities": [],
      "_processing": {
        "log_file_created": "2025-10-25T03:09:07Z"
      }
    },
    {
      "description": "Second reading, passed, yeas 37 nays 10",
      "date": "2025-02-07",
      "organization_id": "~{\"classification\": \"upper\"}",
      "classification": [
        "passage",
        "reading-2"
      ],
      "related_entities": [],
      "_processing": {
        "log_file_created": "2025-10-25T03:09:07Z"
      }
    },
    {
      "description": "Received from Senate",
      "date": "2025-02-10",
      "organization_id": "~{\"classification\": \"lower\"}",
      "classification": [],
      "related_entities": [],
      "_processing": {
        "log_file_created": "2025-10-25T03:09:07Z"
      }
    },
    {
      "description": "Introduced, first reading, referred Transportation Committee",
      "date": "2025-02-18",
      "organization_id": "~{\"classification\": \"lower\"}",
      "classification": [
        "introduction"
      ],
      "related_entities": [],
      "_processing": {
        "log_file_created": "2025-10-25T03:09:07Z"
      }
    },
    {
      "description": "Committee Hearing 11:15",
      "date": "2025-03-13",
      "organization_id": "~{\"classification\": \"lower\"}",
      "classification": [],
      "related_entities": [],
      "_processing": {
        "log_file_created": "2025-10-25T03:09:07Z"
      }
    },
    {
      "description": "Reported back amended, do pass, amendment placed on calendar 6 5 3",
      "date": "2025-03-18",
      "organization_id": "~{\"classification\": \"lower\"}",
      "classification": [
        "committee-passage",
        "committee-passage-favorable"
      ],
      "related_entities": [],
      "_processing": {
        "log_file_created": "2025-10-25T03:09:07Z"
      }
    },
    {
      "description": "Amendment adopted, placed on calendar",
      "date": "2025-03-19",
      "organization_id": "~{\"classification\": \"lower\"}",
      "classification": [],
      "related_entities": [],
      "_processing": {
        "log_file_created": "2025-10-25T03:09:07Z"
      }
    },
    {
      "description": "Second reading, passed as amended, yeas 54 nays 40",
      "date": "2025-03-20",
      "organization_id": "~{\"classification\": \"lower\"}",
      "classification": [
        "passage",
        "reading-2"
      ],
      "related_entities": [],
      "_processing": {
        "log_file_created": "2025-10-25T03:09:07Z"
      }
    },
    {
      "description": "Motion to reconsider failed",
      "date": "2025-03-21",
      "organization_id": "~{\"classification\": \"lower\"}",
      "classification": [],
      "related_entities": [],
      "_processing": {
        "log_file_created": "2025-10-25T03:09:07Z"
      }
    },
    {
      "description": "Returned to Senate (12)",
      "date": "2025-03-21",
      "organization_id": "~{\"classification\": \"upper\"}",
      "classification": [],
      "related_entities": [],
      "_processing": {
        "log_file_created": "2025-10-25T03:09:07Z"
      }
    },
    {
      "description": "Concurred",
      "date": "2025-03-26",
      "organization_id": "~{\"classification\": \"upper\"}",
      "classification": [],
      "related_entities": [],
      "_processing": {
        "log_file_created": "2025-10-25T03:09:07Z"
      }
    },
    {
      "description": "Second reading, passed, yeas 36 nays 11",
      "date": "2025-03-26",
      "organization_id": "~{\"classification\": \"upper\"}",
      "classification": [
        "passage",
        "reading-2"
      ],
      "related_entities": [],
      "_processing": {
        "log_file_created": "2025-10-25T03:09:07Z"
      }
    },
    {
      "description": "Signed by Speaker",
      "date": "2025-03-31",
      "organization_id": "~{\"classification\": \"lower\"}",
      "classification": [],
      "related_entities": [],
      "_processing": {
        "log_file_created": "2025-10-25T03:09:07Z"
      }
    },
    {
      "description": "Signed by President",
      "date": "2025-03-31",
      "organization_id": "~{\"classification\": \"upper\"}",
      "classification": [],
      "related_entities": [],
      "_processing": {
        "log_file_created": "2025-10-25T03:09:07Z"
      }
    },
    {
      "description": "Sent to Governor",
      "date": "2025-03-31",
      "organization_id": "~{\"classification\": \"upper\"}",
      "classification": [
        "executive-receipt"
      ],
      "related_entities": [],
      "_processing": {
        "log_file_created": "2025-10-25T03:09:07Z"
      }
    },
    {
      "description": "Signed by Governor 04/02",
      "date": "2025-04-03",
      "organization_id": "~{\"classification\": \"upper\"}",
      "classification": [
        "executive-signature"
      ],
      "related_entities": [],
      "_processing": {
        "log_file_created": "2025-10-25T03:09:07Z"
      }
    },
    {
      "description": "Filed with Secretary Of State 04/03",
      "date": "2025-04-04",
      "organization_id": "~{\"classification\": \"legislature\"}",
      "classification": [
        "introduction"
      ],
      "related_entities": [],
      "_processing": {
        "log_file_created": "2025-10-25T03:09:07Z"
      }
    }
  ],
  "sponsorships": [
    {
      "name": "Dean Rummel",
      "classification": "primary",
      "entity_type": "person",
      "primary": true,
      "person_id": "~{\"chamber\": \"upper\", \"name\": \"Dean Rummel\"}",
      "organization_id": null
    },
    {
      "name": "Claire Cory",
      "classification": "cosponsor",
      "entity_type": "person",
      "primary": false,
      "person_id": "~{\"chamber\": \"upper\", \"name\": \"Claire Cory\"}",
      "organization_id": null
    },
    {
      "name": "Ty Dressler",
      "classification": "cosponsor",
      "entity_type": "person",
      "primary": false,
      "person_id": "~{\"chamber\": \"lower\", \"name\": \"Ty Dressler\"}",
      "organization_id": null
    },
    {
      "name": "Jerry Klein",
      "classification": "cosponsor",
      "entity_type": "person",
      "primary": false,
      "person_id": "~{\"chamber\": \"upper\", \"name\": \"Jerry Klein\"}",
      "organization_id": null
    },
    {
      "name": "Emily O'Brien",
      "classification": "cosponsor",
      "entity_type": "person",
      "primary": false,
      "person_id": "~{\"chamber\": \"lower\", \"name\": \"Emily O'Brien\"}",
      "organization_id": null
    }
  ],
  "related_bills": [],
  "versions": [
    {
      "note": "INTRODUCED",
      "links": [
        {
          "url": "https://ndlegis.gov/assembly/69-2025/regular/documents/25-1025-02000.pdf",
          "media_type": "application/pdf"
        }
      ],
      "date": "",
      "classification": ""
    },
    {
      "note": "Enrollment",
      "links": [
        {
          "url": "https://ndlegis.gov/assembly/69-2025/regular/documents/25-1025-04000.pdf",
          "media_type": "application/pdf"
        }
      ],
      "date": "",
      "classification": ""
    }
  ],
  "documents": [
    {
      "note": "Adopted by the House Transportation Committee",
      "links": [
        {
          "url": "https://ndlegis.gov/assembly/69-2025/regular/documents/25-1025-02001m.pdf",
          "media_type": "application/pdf"
        }
      ],
      "date": "",
      "classification": ""
    },
    {
      "note": "SENATE BILL NO. 2253 with House Amendments",
      "links": [
        {
          "url": "https://ndlegis.gov/assembly/69-2025/regular/documents/25-1025-03000.pdf",
          "media_type": "application/pdf"
        }
      ],
      "date": "",
      "classification": ""
    }
  ],
  "citations": [],
  "sources": [
    {
      "url": "https://ndlegis.gov/assembly/69-2025/regular/bill-overview/bo2253.html",
      "note": "HTML bill detail page"
    },
    {
      "url": "https://ndlegis.gov/api/assembly/69-2025/data/bills.json",
      "note": "JSON page of session bills"
    }
  ],
  "extras": {},
  "jurisdiction": {
    "id": "ocd-jurisdiction/country:us/state:nd/government",
    "name": "North Dakota",
    "classification": "state",
    "division_id": "ocd-division/country:us/state:nd"
  },
  "_processing": {
    "logs_latest_update": "2025-10-25T03:09:07Z",
    "text_extraction_latest_update": "2025-10-25T09:58:45.171223Z"
  }
}