{
  "legislative_session": "69",
  "identifier": "SB 2393",
  "title": "A BILL for an Act to amend and reenact section 53-06.1-11.2 of the North Dakota Century Code, relating to transfers from the charitable gaming operating fund to the gambling disorder prevention and treatment fund; and to authorize a full-time equivalent position for the department of health and human services.",
  "from_organization": "~{\"classification\": \"upper\"}",
  "classification": [
    "bill"
  ],
  "subject": [],
  "abstracts": [
    {
      "note": "summary",
      "abstract": "Relating to transfers from the charitable gaming operating fund to the gambling disorder prevention and treatment fund; and to authorize a full-time equivalent position for the department of health and human services."
    }
  ],
  "other_titles": [],
  "other_identifiers": [],
  "actions": [
    {
      "description": "Introduced, first reading, referred Judiciary Committee",
      "date": "2025-01-27",
      "organization_id": "~{\"classification\": \"upper\"}",
      "classification": [
        "introduction"
      ],
      "related_entities": [],
      "_processing": {
        "log_file_created": "2025-10-25T03:09:10Z"
      }
    },
    {
      "description": "Committee Hearing 10:30",
      "date": "2025-02-05",
      "organization_id": "~{\"classification\": \"upper\"}",
      "classification": [],
      "related_entities": [],
      "_processing": {
        "log_file_created": "2025-10-25T03:09:10Z"
      }
    },
    {
      "description": "Reported back, do pass  6 1 0",
      "date": "2025-02-11",
      "organization_id": "~{\"classification\": \"upper\"}",
      "classification": [
        "committee-passage",
        "committee-passage-favorable"
      ],
      "related_entities": [],
      "_processing": {
        "log_file_created": "2025-10-25T03:09:10Z"
      }
    },
    {
      "description": "Rereferred to Appropriations",
      "date": "2025-02-11",
      "organization_id": "~{\"classification\": \"upper\"}",
      "classification": [],
      "related_entities": [],
      "_processing": {
        "log_file_created": "2025-10-25T03:09:10Z"
      }
    },
    {
      "description": "Reported back, do not pass, placed on calendar 16 0 0",
      "date": "2025-02-21",
      "organization_id": "~{\"classification\": \"upper\"}",
      "classification": [
        "committee-passage",
        "committee-passage-unfavorable"
      ],
      "related_entities": [],
      "_processing": {
        "log_file_created": "2025-10-25T03:09:10Z"
      }
    },
    {
      "description": "Second reading, failed to pass, yeas 5 nays 42",
      "date": "2025-02-24",
      "organization_id": "~{\"classification\": \"upper\"}",
      "classification": [
        "reading-2"
      ],
      "related_entities": [],
      "_processing": {
        "log_file_created": "2025-10-25T03:09:10Z"
      }
    }
  ],
  "sponsorships": [
    {
      "name": "Larry Luick",
      "classification": "primary",
      "entity_type": "person",
      "primary": true,
      "person_id": "~{\"chamber\": \"upper\", \"name\": \"Larry Luick\"}",
      "organization_id": null
    },
    {
      "name": "Jose L. Castaneda",
      "classification": "cosponsor",
      "entity_type": "person",
      "primary": false,
      "person_id": "~{\"chamber\": \"upper\", \"name\": \"Jose L. Castaneda\"}",
      "organization_id": null
    },
    {
      "name": "Jerry Klein",
      "classification": "cosponsor",
      "entity_type": "person",
      "primary": false,
      "person_id": "~{\"chamber\": \"upper\", \"name\": \"Jerry Klein\"}",
      "organization_id": null
    },
    {
      "name": "Bob Paulson",
      "classification": "cosponsor",
      "entity_type": "person",
      "primary": false,
      "person_id": "~{\"chamber\": \"upper\", \"name\": \"Bob Paulson\"}",
      "organization_id": null
    }
  ],
  "related_bills": [],
  "versions": [
    {
      "note": "INTRODUCED",
      "links": [
        {
          "url": "https://ndlegis.gov/assembly/69-2025/regular/documents/25-1341-01000.pdf",
          "media_type": "application/pdf"
        }
      ],
      "date": "",
      "classification": ""
    }
  ],
  "documents": [],
  "citations": [],
  "sources": [
    {
      "url": "https://ndlegis.gov/assembly/69-2025/regular/bill-overview/bo2393.html",
      "note": "HTML bill detail page"
    },
    {
      "url": "https://ndlegis.gov/api/assembly/69-2025/data/bills.json",
      "note": "JSON page of session bills"
    }
  ],
  "extras": {},
  "jurisdiction": {
    "id": "ocd-jurisdiction/country:us/state:nd/government",
    "name": "North Dakota",
    "classification": "state",
    "division_id": "ocd-division/country:us/state:nd"
  },
  "_processing": {
    "logs_latest_update": "2025-10-25T03:09:10Z",
    "text_extraction_latest_update": "2025-10-25T10:01:24.444335Z"
  }
}