{
  "legislative_session": "69",
  "identifier": "SB 2011",
  "title": "AN ACT to provide an appropriation for defraying the expenses of the highway patrol; to provide for a transfer; and to provide an exemption.",
  "from_organization": "~{\"classification\": \"upper\"}",
  "classification": [
    "bill"
  ],
  "subject": [],
  "abstracts": [],
  "other_titles": [],
  "other_identifiers": [],
  "actions": [
    {
      "description": "Introduced, first reading, referred Appropriations Committee",
      "date": "2025-01-07",
      "organization_id": "~{\"classification\": \"upper\"}",
      "classification": [
        "introduction"
      ],
      "related_entities": [],
      "_processing": {
        "log_file_created": "2025-10-25T03:09:09Z"
      }
    },
    {
      "description": "Committee Hearing 10:00",
      "date": "2025-01-14",
      "organization_id": "~{\"classification\": \"upper\"}",
      "classification": [],
      "related_entities": [],
      "_processing": {
        "log_file_created": "2025-10-25T03:09:09Z"
      }
    },
    {
      "description": "Reported back amended, do pass, amendment placed on calendar 13 0 3",
      "date": "2025-01-30",
      "organization_id": "~{\"classification\": \"upper\"}",
      "classification": [
        "committee-passage",
        "committee-passage-favorable"
      ],
      "related_entities": [],
      "_processing": {
        "log_file_created": "2025-10-25T03:09:09Z"
      }
    },
    {
      "description": "Amendment adopted, placed on calendar",
      "date": "2025-01-31",
      "organization_id": "~{\"classification\": \"upper\"}",
      "classification": [],
      "related_entities": [],
      "_processing": {
        "log_file_created": "2025-10-25T03:09:09Z"
      }
    },
    {
      "description": "Second reading, passed, yeas 46 nays 0",
      "date": "2025-02-03",
      "organization_id": "~{\"classification\": \"upper\"}",
      "classification": [
        "passage",
        "reading-2"
      ],
      "related_entities": [],
      "_processing": {
        "log_file_created": "2025-10-25T03:09:09Z"
      }
    },
    {
      "description": "Received from Senate",
      "date": "2025-02-04",
      "organization_id": "~{\"classification\": \"lower\"}",
      "classification": [],
      "related_entities": [],
      "_processing": {
        "log_file_created": "2025-10-25T03:09:09Z"
      }
    },
    {
      "description": "Introduced, first reading, referred Appropriations Committee",
      "date": "2025-02-18",
      "organization_id": "~{\"classification\": \"lower\"}",
      "classification": [
        "introduction"
      ],
      "related_entities": [],
      "_processing": {
        "log_file_created": "2025-10-25T03:09:09Z"
      }
    },
    {
      "description": "Committee Hearing 02:30",
      "date": "2025-03-06",
      "organization_id": "~{\"classification\": \"lower\"}",
      "classification": [],
      "related_entities": [],
      "_processing": {
        "log_file_created": "2025-10-25T03:09:09Z"
      }
    },
    {
      "description": "Committee Hearing 02:30",
      "date": "2025-03-17",
      "organization_id": "~{\"classification\": \"lower\"}",
      "classification": [],
      "related_entities": [],
      "_processing": {
        "log_file_created": "2025-10-25T03:09:09Z"
      }
    },
    {
      "description": "Reported back amended, do pass, amendment placed on calendar 21 0 2",
      "date": "2025-04-08",
      "organization_id": "~{\"classification\": \"lower\"}",
      "classification": [
        "committee-passage",
        "committee-passage-favorable"
      ],
      "related_entities": [],
      "_processing": {
        "log_file_created": "2025-10-25T03:09:09Z"
      }
    },
    {
      "description": "Amendment adopted, placed on calendar",
      "date": "2025-04-09",
      "organization_id": "~{\"classification\": \"lower\"}",
      "classification": [],
      "related_entities": [],
      "_processing": {
        "log_file_created": "2025-10-25T03:09:09Z"
      }
    },
    {
      "description": "Second reading, passed as amended, yeas 84 nays 6",
      "date": "2025-04-09",
      "organization_id": "~{\"classification\": \"lower\"}",
      "classification": [
        "passage",
        "reading-2"
      ],
      "related_entities": [],
      "_processing": {
        "log_file_created": "2025-10-25T03:09:09Z"
      }
    },
    {
      "description": "Returned to Senate (12)",
      "date": "2025-04-09",
      "organization_id": "~{\"classification\": \"upper\"}",
      "classification": [],
      "related_entities": [],
      "_processing": {
        "log_file_created": "2025-10-25T03:09:09Z"
      }
    },
    {
      "description": "Refused to concur",
      "date": "2025-04-14",
      "organization_id": "~{\"classification\": \"upper\"}",
      "classification": [],
      "related_entities": [],
      "_processing": {
        "log_file_created": "2025-10-25T03:09:09Z"
      }
    },
    {
      "description": "Conference committee appointed Sickler Erbele Burckhard",
      "date": "2025-04-14",
      "organization_id": "~{\"classification\": \"upper\"}",
      "classification": [],
      "related_entities": [],
      "_processing": {
        "log_file_created": "2025-10-25T03:09:09Z"
      }
    },
    {
      "description": "Conference committee appointed Pyle Kempenich Meier",
      "date": "2025-04-15",
      "organization_id": "~{\"classification\": \"lower\"}",
      "classification": [],
      "related_entities": [],
      "_processing": {
        "log_file_created": "2025-10-25T03:09:09Z"
      }
    },
    {
      "description": "Reported back from conference committee, in place of, placed on calendar",
      "date": "2025-04-21",
      "organization_id": "~{\"classification\": \"upper\"}",
      "classification": [
        "committee-passage"
      ],
      "related_entities": [],
      "_processing": {
        "log_file_created": "2025-10-25T03:09:09Z"
      }
    },
    {
      "description": "Conference committee report adopted",
      "date": "2025-04-22",
      "organization_id": "~{\"classification\": \"upper\"}",
      "classification": [],
      "related_entities": [],
      "_processing": {
        "log_file_created": "2025-10-25T03:09:09Z"
      }
    },
    {
      "description": "Second reading, passed, yeas 47 nays 0",
      "date": "2025-04-22",
      "organization_id": "~{\"classification\": \"upper\"}",
      "classification": [
        "passage",
        "reading-2"
      ],
      "related_entities": [],
      "_processing": {
        "log_file_created": "2025-10-25T03:09:09Z"
      }
    },
    {
      "description": "Reported back from conference committee, in place of, placed on calendar",
      "date": "2025-04-22",
      "organization_id": "~{\"classification\": \"lower\"}",
      "classification": [
        "committee-passage"
      ],
      "related_entities": [],
      "_processing": {
        "log_file_created": "2025-10-25T03:09:09Z"
      }
    },
    {
      "description": "Conference committee report adopted",
      "date": "2025-04-24",
      "organization_id": "~{\"classification\": \"lower\"}",
      "classification": [],
      "related_entities": [],
      "_processing": {
        "log_file_created": "2025-10-25T03:09:09Z"
      }
    },
    {
      "description": "Second reading, passed as amended, yeas 92 nays 1",
      "date": "2025-04-24",
      "organization_id": "~{\"classification\": \"lower\"}",
      "classification": [
        "passage",
        "reading-2"
      ],
      "related_entities": [],
      "_processing": {
        "log_file_created": "2025-10-25T03:09:09Z"
      }
    },
    {
      "description": "Signed by Speaker",
      "date": "2025-04-28",
      "organization_id": "~{\"classification\": \"lower\"}",
      "classification": [],
      "related_entities": [],
      "_processing": {
        "log_file_created": "2025-10-25T03:09:09Z"
      }
    },
    {
      "description": "Signed by President",
      "date": "2025-04-29",
      "organization_id": "~{\"classification\": \"upper\"}",
      "classification": [],
      "related_entities": [],
      "_processing": {
        "log_file_created": "2025-10-25T03:09:09Z"
      }
    },
    {
      "description": "Sent to Governor",
      "date": "2025-04-29",
      "organization_id": "~{\"classification\": \"upper\"}",
      "classification": [
        "executive-receipt"
      ],
      "related_entities": [],
      "_processing": {
        "log_file_created": "2025-10-25T03:09:09Z"
      }
    },
    {
      "description": "Signed by Governor 04/30",
      "date": "2025-05-01",
      "organization_id": "~{\"classification\": \"upper\"}",
      "classification": [
        "executive-signature"
      ],
      "related_entities": [],
      "_processing": {
        "log_file_created": "2025-10-25T03:09:09Z"
      }
    },
    {
      "description": "Filed with Secretary Of State 05/01",
      "date": "2025-05-02",
      "organization_id": "~{\"classification\": \"legislature\"}",
      "classification": [
        "introduction"
      ],
      "related_entities": [],
      "_processing": {
        "log_file_created": "2025-10-25T03:09:09Z"
      }
    }
  ],
  "sponsorships": [
    {
      "name": "Appropriations",
      "classification": "primary",
      "entity_type": "organization",
      "primary": true,
      "person_id": null,
      "organization_id": "~{\"chamber\": \"upper\", \"name\": \"Appropriations\"}"
    }
  ],
  "related_bills": [],
  "versions": [
    {
      "note": "INTRODUCED",
      "links": [
        {
          "url": "https://ndlegis.gov/assembly/69-2025/regular/documents/25-0178-01000.pdf",
          "media_type": "application/pdf"
        }
      ],
      "date": "",
      "classification": ""
    },
    {
      "note": "FIRST ENGROSSMENT",
      "links": [
        {
          "url": "https://ndlegis.gov/assembly/69-2025/regular/documents/25-0178-02000.pdf",
          "media_type": "application/pdf"
        }
      ],
      "date": "",
      "classification": ""
    },
    {
      "note": "FIRST ENGROSSMENT with House Amendments",
      "links": [
        {
          "url": "https://ndlegis.gov/assembly/69-2025/regular/documents/25-0178-03000.pdf",
          "media_type": "application/pdf"
        }
      ],
      "date": "",
      "classification": ""
    },
    {
      "note": "FIRST ENGROSSMENT with Senate Amendments",
      "links": [
        {
          "url": "https://ndlegis.gov/assembly/69-2025/regular/documents/25-0178-04000.pdf",
          "media_type": "application/pdf"
        }
      ],
      "date": "",
      "classification": ""
    },
    {
      "note": "Enrollment",
      "links": [
        {
          "url": "https://ndlegis.gov/assembly/69-2025/regular/documents/25-0178-05000.pdf",
          "media_type": "application/pdf"
        }
      ],
      "date": "",
      "classification": ""
    }
  ],
  "documents": [
    {
      "note": "Prepared by the Legislative Council staff for Senate Appropriations - Government Operations Division Committee",
      "links": [
        {
          "url": "https://ndlegis.gov/assembly/69-2025/regular/documents/25-0178-01002m.pdf",
          "media_type": "application/pdf"
        }
      ],
      "date": "",
      "classification": ""
    },
    {
      "note": "Prepared by the Legislative Council staff for House Appropriations - Government Operations Division Committee",
      "links": [
        {
          "url": "https://ndlegis.gov/assembly/69-2025/regular/documents/25-0178-02002m.pdf",
          "media_type": "application/pdf"
        }
      ],
      "date": "",
      "classification": ""
    },
    {
      "note": "Prepared by the Legislative Council staff for Conference Committee",
      "links": [
        {
          "url": "https://ndlegis.gov/assembly/69-2025/regular/documents/25-0178-02003m.pdf",
          "media_type": "application/pdf"
        }
      ],
      "date": "",
      "classification": ""
    }
  ],
  "citations": [],
  "sources": [
    {
      "url": "https://ndlegis.gov/assembly/69-2025/regular/bill-overview/bo2011.html",
      "note": "HTML bill detail page"
    },
    {
      "url": "https://ndlegis.gov/api/assembly/69-2025/data/bills.json",
      "note": "JSON page of session bills"
    }
  ],
  "extras": {},
  "jurisdiction": {
    "id": "ocd-jurisdiction/country:us/state:nd/government",
    "name": "North Dakota",
    "classification": "state",
    "division_id": "ocd-division/country:us/state:nd"
  },
  "_processing": {
    "logs_latest_update": "2025-10-25T03:09:09Z"
  }
}