{
  "legislative_session": "69",
  "identifier": "HB 1109",
  "title": "AN ACT to create and enact three new sections to chapter 25-16 of the North Dakota Century Code, relating to residential care and services for the developmentally disabled; to amend and reenact sections 25-16-01, 25-16-02, 25-16-03, 25-16-03.1, 25-16-04, 25-16-05, 25-16-06, 25-16-07, 25-16-08, 25-16-09, 25-16-12, 25-16-13, 25-16-14, 25-16.1-01, 25-16.1-02, 25-16.1-03, and 25-16.1-04 of the North Dakota Century Code, relating to developmental disability, residential care and services for the developmentally disabled, and receivers for developmentally disabled facilities; to repeal chapter 25-18 of the North Dakota Century Code, relating to fee for service ratesetting for developmentally disabled facilities; and to declare an emergency.",
  "from_organization": "~{\"classification\": \"lower\"}",
  "classification": [
    "bill"
  ],
  "subject": [],
  "abstracts": [
    {
      "note": "summary",
      "abstract": "Relating to residential care and services for the developmentally disabled; to amend and reenact sections 25\u201116\u201101, 25\u201116\u201102, 25\u201116\u201103, 25\u201116\u201103.1, 25\u201116\u201104, 25\u201116\u201105, 25\u201116\u201106, 25\u201116\u201107, 25\u201116\u201108, 25\u201116\u201109, 25\u201116\u201112, 25\u201116\u201113, 25\u201116\u201114, 25\u201116.1\u201101, 25\u201116.1\u201102, 25\u201116.1\u201103, and 25\u201116.1\u201104 of the North Dakota Century Code, relating to developmental disability, residential care and services for the developmentally disabled, and receivers for developmentally disabled facilities; to repeal chapter 25\u201118 of the North Dakota Century Code, relating to fee for service ratesetting for developmentally disabled facilities; and to declare an emergency."
    }
  ],
  "other_titles": [],
  "other_identifiers": [],
  "actions": [
    {
      "description": "Introduced, first reading, referred Human Services Committee",
      "date": "2025-01-07",
      "organization_id": "~{\"classification\": \"lower\"}",
      "classification": [
        "introduction"
      ],
      "related_entities": [],
      "_processing": {
        "log_file_created": "2025-10-25T03:09:07Z"
      }
    },
    {
      "description": "Committee Hearing 10:00",
      "date": "2025-01-14",
      "organization_id": "~{\"classification\": \"lower\"}",
      "classification": [],
      "related_entities": [],
      "_processing": {
        "log_file_created": "2025-10-25T03:09:07Z"
      }
    },
    {
      "description": "Reported back, do pass, place on calendar 12 0 1",
      "date": "2025-01-15",
      "organization_id": "~{\"classification\": \"lower\"}",
      "classification": [
        "committee-passage",
        "committee-passage-favorable"
      ],
      "related_entities": [],
      "_processing": {
        "log_file_created": "2025-10-25T03:09:07Z"
      }
    },
    {
      "description": "Second reading, passed, yeas 93 nays 0",
      "date": "2025-01-16",
      "organization_id": "~{\"classification\": \"lower\"}",
      "classification": [
        "passage",
        "reading-2"
      ],
      "related_entities": [],
      "_processing": {
        "log_file_created": "2025-10-25T03:09:07Z"
      }
    },
    {
      "description": "Received from House",
      "date": "2025-01-17",
      "organization_id": "~{\"classification\": \"upper\"}",
      "classification": [],
      "related_entities": [],
      "_processing": {
        "log_file_created": "2025-10-25T03:09:07Z"
      }
    },
    {
      "description": "Introduced, first reading, referred Human Services Committee",
      "date": "2025-02-05",
      "organization_id": "~{\"classification\": \"upper\"}",
      "classification": [
        "introduction"
      ],
      "related_entities": [],
      "_processing": {
        "log_file_created": "2025-10-25T03:09:07Z"
      }
    },
    {
      "description": "Committee Hearing 09:00",
      "date": "2025-02-11",
      "organization_id": "~{\"classification\": \"upper\"}",
      "classification": [],
      "related_entities": [],
      "_processing": {
        "log_file_created": "2025-10-25T03:09:07Z"
      }
    },
    {
      "description": "Reported back amended, do pass, amendment placed on calendar 6 0 0",
      "date": "2025-03-07",
      "organization_id": "~{\"classification\": \"upper\"}",
      "classification": [
        "committee-passage",
        "committee-passage-favorable"
      ],
      "related_entities": [],
      "_processing": {
        "log_file_created": "2025-10-25T03:09:07Z"
      }
    },
    {
      "description": "Amendment adopted, placed on calendar",
      "date": "2025-03-07",
      "organization_id": "~{\"classification\": \"upper\"}",
      "classification": [],
      "related_entities": [],
      "_processing": {
        "log_file_created": "2025-10-25T03:09:07Z"
      }
    },
    {
      "description": "Second reading, passed, yeas 45 nays 0, Emergency clause carried",
      "date": "2025-03-10",
      "organization_id": "~{\"classification\": \"upper\"}",
      "classification": [
        "passage",
        "reading-2"
      ],
      "related_entities": [],
      "_processing": {
        "log_file_created": "2025-10-25T03:09:07Z"
      }
    },
    {
      "description": "Returned to House (12)",
      "date": "2025-03-11",
      "organization_id": "~{\"classification\": \"lower\"}",
      "classification": [],
      "related_entities": [],
      "_processing": {
        "log_file_created": "2025-10-25T03:09:07Z"
      }
    },
    {
      "description": "Refused to concur",
      "date": "2025-03-19",
      "organization_id": "~{\"classification\": \"lower\"}",
      "classification": [],
      "related_entities": [],
      "_processing": {
        "log_file_created": "2025-10-25T03:09:07Z"
      }
    },
    {
      "description": "Conference committee appointed Rohr Davis Hendrix",
      "date": "2025-03-19",
      "organization_id": "~{\"classification\": \"lower\"}",
      "classification": [],
      "related_entities": [],
      "_processing": {
        "log_file_created": "2025-10-25T03:09:07Z"
      }
    },
    {
      "description": "Conference committee appointed Lee Weston Hogan",
      "date": "2025-03-28",
      "organization_id": "~{\"classification\": \"upper\"}",
      "classification": [],
      "related_entities": [],
      "_processing": {
        "log_file_created": "2025-10-25T03:09:07Z"
      }
    },
    {
      "description": "Reported back from conference committee, placed on calendar (House accept)",
      "date": "2025-04-03",
      "organization_id": "~{\"classification\": \"lower\"}",
      "classification": [
        "committee-passage"
      ],
      "related_entities": [],
      "_processing": {
        "log_file_created": "2025-10-25T03:09:07Z"
      }
    },
    {
      "description": "Conference committee report adopted",
      "date": "2025-04-10",
      "organization_id": "~{\"classification\": \"lower\"}",
      "classification": [],
      "related_entities": [],
      "_processing": {
        "log_file_created": "2025-10-25T03:09:07Z"
      }
    },
    {
      "description": "Second reading, passed, yeas 92 nays 0, Emergency clause carried",
      "date": "2025-04-10",
      "organization_id": "~{\"classification\": \"lower\"}",
      "classification": [
        "passage",
        "reading-2"
      ],
      "related_entities": [],
      "_processing": {
        "log_file_created": "2025-10-25T03:09:07Z"
      }
    },
    {
      "description": "Reported back from conference committee, placed on calendar (House accept)",
      "date": "2025-04-11",
      "organization_id": "~{\"classification\": \"upper\"}",
      "classification": [
        "committee-passage"
      ],
      "related_entities": [],
      "_processing": {
        "log_file_created": "2025-10-25T03:09:07Z"
      }
    },
    {
      "description": "Conference committee report adopted",
      "date": "2025-04-16",
      "organization_id": "~{\"classification\": \"upper\"}",
      "classification": [],
      "related_entities": [],
      "_processing": {
        "log_file_created": "2025-10-25T03:09:07Z"
      }
    },
    {
      "description": "Signed by President",
      "date": "2025-04-21",
      "organization_id": "~{\"classification\": \"upper\"}",
      "classification": [],
      "related_entities": [],
      "_processing": {
        "log_file_created": "2025-10-25T03:09:07Z"
      }
    },
    {
      "description": "Signed by Speaker",
      "date": "2025-04-22",
      "organization_id": "~{\"classification\": \"lower\"}",
      "classification": [],
      "related_entities": [],
      "_processing": {
        "log_file_created": "2025-10-25T03:09:07Z"
      }
    },
    {
      "description": "Sent to Governor",
      "date": "2025-04-22",
      "organization_id": "~{\"classification\": \"lower\"}",
      "classification": [
        "executive-receipt"
      ],
      "related_entities": [],
      "_processing": {
        "log_file_created": "2025-10-25T03:09:07Z"
      }
    },
    {
      "description": "Signed by Governor 04/23",
      "date": "2025-04-24",
      "organization_id": "~{\"classification\": \"lower\"}",
      "classification": [
        "executive-signature"
      ],
      "related_entities": [],
      "_processing": {
        "log_file_created": "2025-10-25T03:09:07Z"
      }
    },
    {
      "description": "Filed with Secretary Of State 04/23",
      "date": "2025-04-25",
      "organization_id": "~{\"classification\": \"legislature\"}",
      "classification": [
        "introduction"
      ],
      "related_entities": [],
      "_processing": {
        "log_file_created": "2025-10-25T03:09:07Z"
      }
    }
  ],
  "sponsorships": [
    {
      "name": "Human Services",
      "classification": "primary",
      "entity_type": "organization",
      "primary": true,
      "person_id": null,
      "organization_id": "~{\"chamber\": \"lower\", \"name\": \"Human Services\"}"
    }
  ],
  "related_bills": [],
  "versions": [
    {
      "note": "INTRODUCED",
      "links": [
        {
          "url": "https://ndlegis.gov/assembly/69-2025/regular/documents/25-8079-01000.pdf",
          "media_type": "application/pdf"
        }
      ],
      "date": "",
      "classification": ""
    },
    {
      "note": "Enrollment",
      "links": [
        {
          "url": "https://ndlegis.gov/assembly/69-2025/regular/documents/25-8079-03000.pdf",
          "media_type": "application/pdf"
        }
      ],
      "date": "",
      "classification": ""
    }
  ],
  "documents": [
    {
      "note": "Adopted by the Senate Human Services Committee",
      "links": [
        {
          "url": "https://ndlegis.gov/assembly/69-2025/regular/documents/25-8079-01001m.pdf",
          "media_type": "application/pdf"
        }
      ],
      "date": "",
      "classification": ""
    },
    {
      "note": "HOUSE BILL NO. 1109 with Senate Amendments",
      "links": [
        {
          "url": "https://ndlegis.gov/assembly/69-2025/regular/documents/25-8079-02000.pdf",
          "media_type": "application/pdf"
        }
      ],
      "date": "",
      "classification": ""
    }
  ],
  "citations": [],
  "sources": [
    {
      "url": "https://ndlegis.gov/assembly/69-2025/regular/bill-overview/bo1109.html",
      "note": "HTML bill detail page"
    },
    {
      "url": "https://ndlegis.gov/api/assembly/69-2025/data/bills.json",
      "note": "JSON page of session bills"
    }
  ],
  "extras": {},
  "jurisdiction": {
    "id": "ocd-jurisdiction/country:us/state:nd/government",
    "name": "North Dakota",
    "classification": "state",
    "division_id": "ocd-division/country:us/state:nd"
  },
  "_processing": {
    "logs_latest_update": "2025-10-25T03:09:07Z",
    "text_extraction_latest_update": "2025-10-25T09:26:23.579125Z"
  }
}