{
  "legislative_session": "69",
  "identifier": "SB 2233",
  "title": "AN ACT to amend and reenact section 32-12.2-04 of the North Dakota Century Code, relating to notice requirements for claims against the state.",
  "from_organization": "~{\"classification\": \"upper\"}",
  "classification": [
    "bill"
  ],
  "subject": [],
  "abstracts": [
    {
      "note": "summary",
      "abstract": "Relating to notice requirements for claims against the state."
    }
  ],
  "other_titles": [],
  "other_identifiers": [],
  "actions": [
    {
      "description": "Introduced, first reading, referred Judiciary Committee",
      "date": "2025-01-17",
      "organization_id": "~{\"classification\": \"upper\"}",
      "classification": [
        "introduction"
      ],
      "related_entities": [],
      "_processing": {
        "log_file_created": "2025-10-25T03:09:08Z"
      }
    },
    {
      "description": "Committee Hearing 02:30",
      "date": "2025-01-28",
      "organization_id": "~{\"classification\": \"upper\"}",
      "classification": [],
      "related_entities": [],
      "_processing": {
        "log_file_created": "2025-10-25T03:09:08Z"
      }
    },
    {
      "description": "Reported back, do pass, place on calendar 7 0 0",
      "date": "2025-01-29",
      "organization_id": "~{\"classification\": \"upper\"}",
      "classification": [
        "committee-passage",
        "committee-passage-favorable"
      ],
      "related_entities": [],
      "_processing": {
        "log_file_created": "2025-10-25T03:09:08Z"
      }
    },
    {
      "description": "Second reading, passed, yeas 45 nays 0",
      "date": "2025-01-30",
      "organization_id": "~{\"classification\": \"upper\"}",
      "classification": [
        "passage",
        "reading-2"
      ],
      "related_entities": [],
      "_processing": {
        "log_file_created": "2025-10-25T03:09:08Z"
      }
    },
    {
      "description": "Received from Senate",
      "date": "2025-01-31",
      "organization_id": "~{\"classification\": \"lower\"}",
      "classification": [],
      "related_entities": [],
      "_processing": {
        "log_file_created": "2025-10-25T03:09:08Z"
      }
    },
    {
      "description": "Introduced, first reading, referred Government and Veterans Affairs Committee",
      "date": "2025-02-18",
      "organization_id": "~{\"classification\": \"lower\"}",
      "classification": [
        "introduction"
      ],
      "related_entities": [],
      "_processing": {
        "log_file_created": "2025-10-25T03:09:08Z"
      }
    },
    {
      "description": "Committee Hearing 03:00",
      "date": "2025-03-06",
      "organization_id": "~{\"classification\": \"lower\"}",
      "classification": [],
      "related_entities": [],
      "_processing": {
        "log_file_created": "2025-10-25T03:09:08Z"
      }
    },
    {
      "description": "Reported back, do pass, place on calendar 11 0 3",
      "date": "2025-03-21",
      "organization_id": "~{\"classification\": \"lower\"}",
      "classification": [
        "committee-passage",
        "committee-passage-favorable"
      ],
      "related_entities": [],
      "_processing": {
        "log_file_created": "2025-10-25T03:09:08Z"
      }
    },
    {
      "description": "Second reading, passed, yeas 88 nays 3",
      "date": "2025-03-26",
      "organization_id": "~{\"classification\": \"lower\"}",
      "classification": [
        "passage",
        "reading-2"
      ],
      "related_entities": [],
      "_processing": {
        "log_file_created": "2025-10-25T03:09:08Z"
      }
    },
    {
      "description": "Returned to Senate",
      "date": "2025-03-27",
      "organization_id": "~{\"classification\": \"upper\"}",
      "classification": [],
      "related_entities": [],
      "_processing": {
        "log_file_created": "2025-10-25T03:09:08Z"
      }
    },
    {
      "description": "Signed by Speaker",
      "date": "2025-03-31",
      "organization_id": "~{\"classification\": \"lower\"}",
      "classification": [],
      "related_entities": [],
      "_processing": {
        "log_file_created": "2025-10-25T03:09:08Z"
      }
    },
    {
      "description": "Signed by President",
      "date": "2025-03-31",
      "organization_id": "~{\"classification\": \"upper\"}",
      "classification": [],
      "related_entities": [],
      "_processing": {
        "log_file_created": "2025-10-25T03:09:08Z"
      }
    },
    {
      "description": "Sent to Governor",
      "date": "2025-03-31",
      "organization_id": "~{\"classification\": \"upper\"}",
      "classification": [
        "executive-receipt"
      ],
      "related_entities": [],
      "_processing": {
        "log_file_created": "2025-10-25T03:09:08Z"
      }
    },
    {
      "description": "Signed by Governor 04/02",
      "date": "2025-04-03",
      "organization_id": "~{\"classification\": \"upper\"}",
      "classification": [
        "executive-signature"
      ],
      "related_entities": [],
      "_processing": {
        "log_file_created": "2025-10-25T03:09:08Z"
      }
    },
    {
      "description": "Filed with Secretary Of State 04/03",
      "date": "2025-04-04",
      "organization_id": "~{\"classification\": \"legislature\"}",
      "classification": [
        "introduction"
      ],
      "related_entities": [],
      "_processing": {
        "log_file_created": "2025-10-25T03:09:08Z"
      }
    }
  ],
  "sponsorships": [
    {
      "name": "Jonathan Sickler",
      "classification": "primary",
      "entity_type": "person",
      "primary": true,
      "person_id": "~{\"chamber\": \"upper\", \"name\": \"Jonathan Sickler\"}",
      "organization_id": null
    },
    {
      "name": "Claire Cory",
      "classification": "cosponsor",
      "entity_type": "person",
      "primary": false,
      "person_id": "~{\"chamber\": \"upper\", \"name\": \"Claire Cory\"}",
      "organization_id": null
    },
    {
      "name": "Diane Larson",
      "classification": "cosponsor",
      "entity_type": "person",
      "primary": false,
      "person_id": "~{\"chamber\": \"upper\", \"name\": \"Diane Larson\"}",
      "organization_id": null
    },
    {
      "name": "Steve Vetter",
      "classification": "cosponsor",
      "entity_type": "person",
      "primary": false,
      "person_id": "~{\"chamber\": \"lower\", \"name\": \"Steve Vetter\"}",
      "organization_id": null
    }
  ],
  "related_bills": [],
  "versions": [
    {
      "note": "INTRODUCED",
      "links": [
        {
          "url": "https://ndlegis.gov/assembly/69-2025/regular/documents/25-0887-02000.pdf",
          "media_type": "application/pdf"
        }
      ],
      "date": "",
      "classification": ""
    },
    {
      "note": "Enrollment",
      "links": [
        {
          "url": "https://ndlegis.gov/assembly/69-2025/regular/documents/25-0887-03000.pdf",
          "media_type": "application/pdf"
        }
      ],
      "date": "",
      "classification": ""
    }
  ],
  "documents": [],
  "citations": [],
  "sources": [
    {
      "url": "https://ndlegis.gov/assembly/69-2025/regular/bill-overview/bo2233.html",
      "note": "HTML bill detail page"
    },
    {
      "url": "https://ndlegis.gov/api/assembly/69-2025/data/bills.json",
      "note": "JSON page of session bills"
    }
  ],
  "extras": {},
  "jurisdiction": {
    "id": "ocd-jurisdiction/country:us/state:nd/government",
    "name": "North Dakota",
    "classification": "state",
    "division_id": "ocd-division/country:us/state:nd"
  },
  "_processing": {
    "logs_latest_update": "2025-10-25T03:09:08Z"
  }
}