{
  "legislative_session": "69",
  "identifier": "HB 1184",
  "title": "A BILL for an Act to create and enact a new section to chapter 15-01, a new section to chapter 21-10, and a new section to chapter 54-11 of the North Dakota Century Code, relating to digital asset and precious metal investments.",
  "from_organization": "~{\"classification\": \"lower\"}",
  "classification": [
    "bill"
  ],
  "subject": [],
  "abstracts": [
    {
      "note": "summary",
      "abstract": "Relating to digital asset and precious metal investments."
    }
  ],
  "other_titles": [],
  "other_identifiers": [],
  "actions": [
    {
      "description": "Introduced, first reading, referred Industry, Business and Labor Committee",
      "date": "2025-01-07",
      "organization_id": "~{\"classification\": \"lower\"}",
      "classification": [
        "introduction"
      ],
      "related_entities": [],
      "_processing": {
        "log_file_created": "2025-10-25T03:09:09Z"
      }
    },
    {
      "description": "Committee Hearing 09:00",
      "date": "2025-01-14",
      "organization_id": "~{\"classification\": \"lower\"}",
      "classification": [],
      "related_entities": [],
      "_processing": {
        "log_file_created": "2025-10-25T03:09:09Z"
      }
    },
    {
      "description": "Reported back, do not pass, placed on calendar 6 5 3",
      "date": "2025-01-29",
      "organization_id": "~{\"classification\": \"lower\"}",
      "classification": [
        "committee-passage",
        "committee-passage-unfavorable"
      ],
      "related_entities": [],
      "_processing": {
        "log_file_created": "2025-10-25T03:09:09Z"
      }
    },
    {
      "description": "Second reading, failed to pass, yeas 32 nays 57",
      "date": "2025-01-31",
      "organization_id": "~{\"classification\": \"lower\"}",
      "classification": [
        "reading-2"
      ],
      "related_entities": [],
      "_processing": {
        "log_file_created": "2025-10-25T03:09:09Z"
      }
    }
  ],
  "sponsorships": [
    {
      "name": "Nathan Toman",
      "classification": "primary",
      "entity_type": "person",
      "primary": true,
      "person_id": "~{\"chamber\": \"lower\", \"name\": \"Nathan Toman\"}",
      "organization_id": null
    },
    {
      "name": "Jeff Barta",
      "classification": "cosponsor",
      "entity_type": "person",
      "primary": false,
      "person_id": "~{\"chamber\": \"upper\", \"name\": \"Jeff Barta\"}",
      "organization_id": null
    },
    {
      "name": "Josh Christy",
      "classification": "cosponsor",
      "entity_type": "person",
      "primary": false,
      "person_id": "~{\"chamber\": \"lower\", \"name\": \"Josh Christy\"}",
      "organization_id": null
    },
    {
      "name": "Claire Cory",
      "classification": "cosponsor",
      "entity_type": "person",
      "primary": false,
      "person_id": "~{\"chamber\": \"upper\", \"name\": \"Claire Cory\"}",
      "organization_id": null
    },
    {
      "name": "Matthew Heilman",
      "classification": "cosponsor",
      "entity_type": "person",
      "primary": false,
      "person_id": "~{\"chamber\": \"lower\", \"name\": \"Matthew Heilman\"}",
      "organization_id": null
    },
    {
      "name": "Jared Hendrix",
      "classification": "cosponsor",
      "entity_type": "person",
      "primary": false,
      "person_id": "~{\"chamber\": \"lower\", \"name\": \"Jared Hendrix\"}",
      "organization_id": null
    },
    {
      "name": "Daniel Johnston",
      "classification": "cosponsor",
      "entity_type": "person",
      "primary": false,
      "person_id": "~{\"chamber\": \"lower\", \"name\": \"Daniel Johnston\"}",
      "organization_id": null
    },
    {
      "name": "Scott Meyer",
      "classification": "cosponsor",
      "entity_type": "person",
      "primary": false,
      "person_id": "~{\"chamber\": \"upper\", \"name\": \"Scott Meyer\"}",
      "organization_id": null
    },
    {
      "name": "SuAnn Olson",
      "classification": "cosponsor",
      "entity_type": "person",
      "primary": false,
      "person_id": "~{\"chamber\": \"lower\", \"name\": \"SuAnn Olson\"}",
      "organization_id": null
    },
    {
      "name": "Bob Paulson",
      "classification": "cosponsor",
      "entity_type": "person",
      "primary": false,
      "person_id": "~{\"chamber\": \"upper\", \"name\": \"Bob Paulson\"}",
      "organization_id": null
    },
    {
      "name": "Todd Porter",
      "classification": "cosponsor",
      "entity_type": "person",
      "primary": false,
      "person_id": "~{\"chamber\": \"lower\", \"name\": \"Todd Porter\"}",
      "organization_id": null
    }
  ],
  "related_bills": [],
  "versions": [
    {
      "note": "INTRODUCED",
      "links": [
        {
          "url": "https://ndlegis.gov/assembly/69-2025/regular/documents/25-0515-03000.pdf",
          "media_type": "application/pdf"
        }
      ],
      "date": "",
      "classification": ""
    }
  ],
  "documents": [],
  "citations": [],
  "sources": [
    {
      "url": "https://ndlegis.gov/assembly/69-2025/regular/bill-overview/bo1184.html",
      "note": "HTML bill detail page"
    },
    {
      "url": "https://ndlegis.gov/api/assembly/69-2025/data/bills.json",
      "note": "JSON page of session bills"
    }
  ],
  "extras": {},
  "jurisdiction": {
    "id": "ocd-jurisdiction/country:us/state:nd/government",
    "name": "North Dakota",
    "classification": "state",
    "division_id": "ocd-division/country:us/state:nd"
  },
  "_processing": {
    "logs_latest_update": "2025-10-25T03:09:09Z",
    "text_extraction_latest_update": "2025-10-25T09:41:16.948148Z"
  }
}