{
  "legislative_session": "69",
  "identifier": "HB 1523",
  "title": "A BILL for an Act to provide an appropriation to the parks and recreation department for a ski resort infrastructure grant; and to declare an emergency.",
  "from_organization": "~{\"classification\": \"lower\"}",
  "classification": [
    "bill"
  ],
  "subject": [],
  "abstracts": [],
  "other_titles": [],
  "other_identifiers": [],
  "actions": [
    {
      "description": "Introduced, first reading, referred Agriculture Committee",
      "date": "2025-01-20",
      "organization_id": "~{\"classification\": \"lower\"}",
      "classification": [
        "introduction"
      ],
      "related_entities": [],
      "_processing": {
        "log_file_created": "2025-10-25T03:09:07Z"
      }
    },
    {
      "description": "Committee Hearing 11:00",
      "date": "2025-01-30",
      "organization_id": "~{\"classification\": \"lower\"}",
      "classification": [],
      "related_entities": [],
      "_processing": {
        "log_file_created": "2025-10-25T03:09:07Z"
      }
    },
    {
      "description": "Reported back amended, do not pass, placed on calendar 8 5 1",
      "date": "2025-02-03",
      "organization_id": "~{\"classification\": \"lower\"}",
      "classification": [
        "committee-passage",
        "committee-passage-unfavorable"
      ],
      "related_entities": [],
      "_processing": {
        "log_file_created": "2025-10-25T03:09:07Z"
      }
    },
    {
      "description": "Amendment adopted, placed on calendar",
      "date": "2025-02-04",
      "organization_id": "~{\"classification\": \"lower\"}",
      "classification": [],
      "related_entities": [],
      "_processing": {
        "log_file_created": "2025-10-25T03:09:07Z"
      }
    },
    {
      "description": "Second reading, failed to pass, yeas 39 nays 52",
      "date": "2025-02-05",
      "organization_id": "~{\"classification\": \"lower\"}",
      "classification": [
        "reading-2"
      ],
      "related_entities": [],
      "_processing": {
        "log_file_created": "2025-10-25T03:09:07Z"
      }
    }
  ],
  "sponsorships": [
    {
      "name": "David Monson",
      "classification": "primary",
      "entity_type": "person",
      "primary": true,
      "person_id": "~{\"chamber\": \"lower\", \"name\": \"David Monson\"}",
      "organization_id": null
    },
    {
      "name": "Karen A. Anderson",
      "classification": "cosponsor",
      "entity_type": "person",
      "primary": false,
      "person_id": "~{\"chamber\": \"lower\", \"name\": \"Karen A. Anderson\"}",
      "organization_id": null
    },
    {
      "name": "Claire Cory",
      "classification": "cosponsor",
      "entity_type": "person",
      "primary": false,
      "person_id": "~{\"chamber\": \"upper\", \"name\": \"Claire Cory\"}",
      "organization_id": null
    },
    {
      "name": "Zachary Ista",
      "classification": "cosponsor",
      "entity_type": "person",
      "primary": false,
      "person_id": "~{\"chamber\": \"lower\", \"name\": \"Zachary Ista\"}",
      "organization_id": null
    },
    {
      "name": "Bob Martinson",
      "classification": "cosponsor",
      "entity_type": "person",
      "primary": false,
      "person_id": "~{\"chamber\": \"lower\", \"name\": \"Bob Martinson\"}",
      "organization_id": null
    },
    {
      "name": "Scott Meyer",
      "classification": "cosponsor",
      "entity_type": "person",
      "primary": false,
      "person_id": "~{\"chamber\": \"upper\", \"name\": \"Scott Meyer\"}",
      "organization_id": null
    },
    {
      "name": "Janne Myrdal",
      "classification": "cosponsor",
      "entity_type": "person",
      "primary": false,
      "person_id": "~{\"chamber\": \"upper\", \"name\": \"Janne Myrdal\"}",
      "organization_id": null
    },
    {
      "name": "Mark Sanford",
      "classification": "cosponsor",
      "entity_type": "person",
      "primary": false,
      "person_id": "~{\"chamber\": \"lower\", \"name\": \"Mark Sanford\"}",
      "organization_id": null
    },
    {
      "name": "Steve Swiontek",
      "classification": "cosponsor",
      "entity_type": "person",
      "primary": false,
      "person_id": "~{\"chamber\": \"lower\", \"name\": \"Steve Swiontek\"}",
      "organization_id": null
    },
    {
      "name": "Kent Weston",
      "classification": "cosponsor",
      "entity_type": "person",
      "primary": false,
      "person_id": "~{\"chamber\": \"upper\", \"name\": \"Kent Weston\"}",
      "organization_id": null
    }
  ],
  "related_bills": [],
  "versions": [
    {
      "note": "INTRODUCED",
      "links": [
        {
          "url": "https://ndlegis.gov/assembly/69-2025/regular/documents/25-1210-01000.pdf",
          "media_type": "application/pdf"
        }
      ],
      "date": "",
      "classification": ""
    },
    {
      "note": "FIRST ENGROSSMENT",
      "links": [
        {
          "url": "https://ndlegis.gov/assembly/69-2025/regular/documents/25-1210-02000.pdf",
          "media_type": "application/pdf"
        }
      ],
      "date": "",
      "classification": ""
    }
  ],
  "documents": [
    {
      "note": "Adopted by the House Agriculture Committee",
      "links": [
        {
          "url": "https://ndlegis.gov/assembly/69-2025/regular/documents/25-1210-01001m.pdf",
          "media_type": "application/pdf"
        }
      ],
      "date": "",
      "classification": ""
    }
  ],
  "citations": [],
  "sources": [
    {
      "url": "https://ndlegis.gov/assembly/69-2025/regular/bill-overview/bo1523.html",
      "note": "HTML bill detail page"
    },
    {
      "url": "https://ndlegis.gov/api/assembly/69-2025/data/bills.json",
      "note": "JSON page of session bills"
    }
  ],
  "extras": {},
  "jurisdiction": {
    "id": "ocd-jurisdiction/country:us/state:nd/government",
    "name": "North Dakota",
    "classification": "state",
    "division_id": "ocd-division/country:us/state:nd"
  },
  "_processing": {
    "logs_latest_update": "2025-10-25T03:09:07Z",
    "text_extraction_latest_update": "2025-10-25T09:54:31.766050Z"
  }
}